yocli/__init__.py
yocli/main.py
yocli/menu.py
yocli/ssh.py
yocli/utils.py
yocli/vscode.py
yocli_tools-0.1.3.dist-info/METADATA
yocli_tools-0.1.3.dist-info/WHEEL
yocli_tools-0.1.3.dist-info/entry_points.txt
yocli_tools-0.1.3.dist-info/top_level.txt
yocli_tools-0.1.3.dist-info/RECORD
