Metadata-Version: 2.1
Name: yocli-tools
Version: 0.1.3
Summary: A CLI tool to manage SSH connections and VSCode projects
Home-page: https://github.com/yoannes/yocli
Author: Yo
Author-email: yoannes@gmail.com
Classifier: Programming Language :: Python :: 3
Classifier: License :: OSI Approved :: MIT License
Classifier: Operating System :: OS Independent
Requires-Python: >=3.6
Requires-Dist: pyyaml
